tidypython/__init__.py
tidypython/gather.py
tidypython/separate.py
tidypython/spread.py
tidypython-0.0.1.dev3.dist-info/METADATA
tidypython-0.0.1.dev3.dist-info/WHEEL
tidypython-0.0.1.dev3.dist-info/top_level.txt
tidypython-0.0.1.dev3.dist-info/RECORD
