Metadata-Version: 2.1
Name: tidypython
Version: 0.0.1.dev3
Summary: A package designed to syntactically mimic the tidyr R package
Home-page: https://github.com/durrantmm/tidypython
Author: Matt Durrant
Author-email: matthewgeorgedurrant@gmail.com
License: UNKNOWN
Keywords: tidyr R syntax
Platform: UNKNOWN
